discobase/__about__.py
discobase/__init__.py
discobase/_cursor.py
discobase/_metadata.py
discobase/_util.py
discobase/database.py
discobase/exceptions.py
discobase/py.typed
discobase/table.py
discobase/cogs/utility.py
discobase/cogs/visualization.py
discobase/ui/embed.py
discobase-1.0.0b0.dist-info/METADATA
discobase-1.0.0b0.dist-info/WHEEL
discobase-1.0.0b0.dist-info/licenses/LICENSE.txt
discobase-1.0.0b0.dist-info/RECORD
