Metadata-Version: 2.3
Name: discobase
Version: 1.0.0b0
License-Expression: MIT
License-File: LICENSE.txt
Requires-Dist: aiocache
Requires-Dist: discord-py
Requires-Dist: loguru
Requires-Dist: pydantic
Requires-Dist: typing-extensions
